liviu_primul_project/__init__.py
liviu_primul_proiect-0.1.0.dist-info/METADATA
liviu_primul_proiect-0.1.0.dist-info/WHEEL
liviu_primul_proiect-0.1.0.dist-info/top_level.txt
liviu_primul_proiect-0.1.0.dist-info/RECORD
