Metadata-Version: 2.1
Name: liviu-primul-proiect
Version: 0.1.0
Summary: Say Hello from Liviu
Author: Liviu Andrei
Author-email: liviu.andrei.la@gmail.com
License: UNKNOWN
Platform: UNKNOWN
Requires-Dist: dinosay
